ollama/__init__.py
ollama/__main__.py
ollama/cmd/__init__.py
ollama/cmd/cli.py
ollama/cmd/server.py
ollama/engine.py
ollama/model.py
ollama/prompt.py
ollama/templates/alpaca.prompt
ollama/templates/falcon.prompt
ollama/templates/gpt4.prompt
ollama/templates/hermes.prompt
ollama/templates/mpt.prompt
ollama/templates/oasst.prompt
ollama/templates/orca.prompt
ollama/templates/qlora.prompt
ollama/templates/tulu.prompt
ollama/templates/ultralm.prompt
ollama/templates/vicuna.prompt
ollama/templates/wizardcoder.prompt
ollama/templates/wizardlm.prompt
ollama-0.0.9.dist-info/LICENSE
ollama-0.0.9.dist-info/METADATA
ollama-0.0.9.dist-info/WHEEL
ollama-0.0.9.dist-info/entry_points.txt
ollama-0.0.9.dist-info/RECORD
