Metadata-Version: 2.1
Name: ollama
Version: 0.0.9
Summary: Run ai models locally
Author: ollama team
Requires-Python: >=3.8,<4.0
Classifier: Programming Language :: Python :: 3
Classifier: Programming Language :: Python :: 3.8
Classifier: Programming Language :: Python :: 3.9
Classifier: Programming Language :: Python :: 3.10
Classifier: Programming Language :: Python :: 3.11
Requires-Dist: aiohttp (>=3.8.4,<4.0.0)
Requires-Dist: aiohttp-cors (>=0.7.0,<0.8.0)
Requires-Dist: ctransformers (>=0.2.10,<0.3.0)
Requires-Dist: fuzzywuzzy[speedup] (>=0.18.0,<0.19.0)
Requires-Dist: jinja2 (>=3.1.2,<4.0.0)
Requires-Dist: llama-cpp-python (>=0.1.67,<0.2.0)
Requires-Dist: requests (>=2.31.0,<3.0.0)
Requires-Dist: tqdm (>=4.65.0,<5.0.0)
Requires-Dist: validators (>=0.20.0,<0.21.0)
Requires-Dist: yaspin (>=2.3.0,<3.0.0)
